odoo8_addon_l10n_pe_invoice-8.0.1.1.0-py2.7-nspkg.pth
odoo8_addon_l10n_pe_invoice-8.0.1.1.0.dist-info/top_level.txt
odoo8_addon_l10n_pe_invoice-8.0.1.1.0.dist-info/WHEEL
odoo8_addon_l10n_pe_invoice-8.0.1.1.0.dist-info/RECORD
odoo8_addon_l10n_pe_invoice-8.0.1.1.0.dist-info/metadata.json
odoo8_addon_l10n_pe_invoice-8.0.1.1.0.dist-info/DESCRIPTION.rst
odoo8_addon_l10n_pe_invoice-8.0.1.1.0.dist-info/METADATA
odoo8_addon_l10n_pe_invoice-8.0.1.1.0.dist-info/namespace_packages.txt
odoo_addons/l10n_pe_invoice/__openerp__.py
odoo_addons/l10n_pe_invoice/__init__.py
odoo_addons/l10n_pe_invoice/README.rst
odoo_addons/l10n_pe_invoice/view/invoice_conf_view.xml
odoo_addons/l10n_pe_invoice/view/account_invoice_sup_inv_num_req.xml
odoo_addons/l10n_pe_invoice/i18n/es.po
odoo_addons/l10n_pe_invoice/i18n/es_PE.po
odoo_addons/l10n_pe_invoice/model/supplier_invoice_validation.py
odoo_addons/l10n_pe_invoice/model/invoice_conf_installer.py
odoo_addons/l10n_pe_invoice/model/__init__.py
odoo_addons/l10n_pe_invoice/model/invoice.py
odoo_addons/l10n_pe_invoice/test/limit_amount_inv.yml
odoo_addons/l10n_pe_invoice/workflow/invoice_workflow.xml
