Metadata-Version: 2.0
Name: odoo8-addon-l10n-pe-invoice
Version: 8.0.1.1.0
Summary: RUC and DNI Validation on Invoice
Home-page: http://www.openerp.com
Author: UNKNOWN
Author-email: UNKNOWN
License: AGPL-3
Platform: UNKNOWN
Requires-Dist: odoo (<9.0a,>=8.0a)
Requires-Dist: odoo8-addon-l10n-pe-multifunctions
Classifier: Programming Language :: Python :: 2.7
Classifier: Framework :: Odoo
Classifier: License :: OSI Approved :: GNU Affero General Public License v3
